MANIFEST.in
Makefile
README.txt
TODO.txt
bootstrap.py
buildout.cfg
setup.py
docs/HISTORY.txt
src/plone/__init__.py
src/plone.app.referenceintegrity.egg-info/PKG-INFO
src/plone.app.referenceintegrity.egg-info/SOURCES.txt
src/plone.app.referenceintegrity.egg-info/dependency_links.txt
src/plone.app.referenceintegrity.egg-info/entry_points.txt
src/plone.app.referenceintegrity.egg-info/namespace_packages.txt
src/plone.app.referenceintegrity.egg-info/not-zip-safe
src/plone.app.referenceintegrity.egg-info/requires.txt
src/plone.app.referenceintegrity.egg-info/top_level.txt
src/plone/app/__init__.py
src/plone/app/referenceintegrity/TODO.txt
src/plone/app/referenceintegrity/__init__.py
src/plone/app/referenceintegrity/config.py
src/plone/app/referenceintegrity/configure.zcml
src/plone/app/referenceintegrity/handlers.py
src/plone/app/referenceintegrity/interfaces.py
src/plone/app/referenceintegrity/testing.py
src/plone/app/referenceintegrity/vocabularies.py
src/plone/app/referenceintegrity/profiles/default/metadata.xml
src/plone/app/referenceintegrity/profiles/default/registry.xml
src/plone/app/referenceintegrity/tests/__init__.py
src/plone/app/referenceintegrity/tests/test_config.py
src/plone/app/referenceintegrity/tests/test_handlers.py
src/plone/app/referenceintegrity/tests/test_vocabularies.py