Metadata-Version: 2.1
Name: plone.app.referenceintegrity
Version: 0.1
Summary: Protect reference targets to be deleted
Home-page: http://svn.plone.org/svn/collective/
Author: 
Author-email: 
License: GPL
Platform: UNKNOWN
Classifier: Programming Language :: Python
Provides-Extra: test
